obp_api/__init__.py
obp_api/_base_client.py
obp_api/_client.py
obp_api/_compat.py
obp_api/_constants.py
obp_api/_exceptions.py
obp_api/_files.py
obp_api/_models.py
obp_api/_qs.py
obp_api/_resource.py
obp_api/_response.py
obp_api/_streaming.py
obp_api/_types.py
obp_api/_version.py
obp_api/py.typed
obp_api/_utils/__init__.py
obp_api/_utils/_logs.py
obp_api/_utils/_proxy.py
obp_api/_utils/_reflection.py
obp_api/_utils/_streams.py
obp_api/_utils/_sync.py
obp_api/_utils/_transform.py
obp_api/_utils/_typing.py
obp_api/_utils/_utils.py
obp_api/lib/.keep
obp_api/resources/__init__.py
obp_api/resources/accounts_held.py
obp_api/resources/adapter.py
obp_api/resources/authentication_type_validations.py
obp_api/resources/certs.py
obp_api/resources/config.py
obp_api/resources/connector_methods.py
obp_api/resources/consent.py
obp_api/resources/consent_requests.py
obp_api/resources/correlated_entities.py
obp_api/resources/crm_events.py
obp_api/resources/currencies.py
obp_api/resources/customer_account_links.py
obp_api/resources/customers_minimal.py
obp_api/resources/dynamic_entities.py
obp_api/resources/dynamic_message_docs.py
obp_api/resources/endpoint_mappings.py
obp_api/resources/entitlement_requests.py
obp_api/resources/entitlements.py
obp_api/resources/fast_firehose_accounts.py
obp_api/resources/json_schema_validations.py
obp_api/resources/jwks_uris.py
obp_api/resources/method_routings.py
obp_api/resources/permissions.py
obp_api/resources/product_collections.py
obp_api/resources/product_tree.py
obp_api/resources/rate_limits.py
obp_api/resources/regulated_entities.py
obp_api/resources/resource_docs.py
obp_api/resources/roles.py
obp_api/resources/sandbox.py
obp_api/resources/spaces.py
obp_api/resources/standing_orders.py
obp_api/resources/system_dynamic_entities.py
obp_api/resources/user_entitlements.py
obp_api/resources/webui_props.py
obp_api/resources/account_products/__init__.py
obp_api/resources/account_products/account_products.py
obp_api-0.1.0a1.dist-info/METADATA
obp_api-0.1.0a1.dist-info/WHEEL
obp_api-0.1.0a1.dist-info/licenses/LICENSE
obp_api-0.1.0a1.dist-info/RECORD
